LICENSE.txt
MANIFEST.in
README.rst
setup.py
sftpman_gtk/__init__.py
sftpman_gtk/gui.py
sftpman_gtk/helper.py
sftpman_gtk/launcher.py
sftpman_gtk.egg-info/PKG-INFO
sftpman_gtk.egg-info/SOURCES.txt
sftpman_gtk.egg-info/dependency_links.txt
sftpman_gtk.egg-info/entry_points.txt
sftpman_gtk.egg-info/not-zip-safe
sftpman_gtk.egg-info/requires.txt
sftpman_gtk.egg-info/top_level.txt