Metadata-Version: 2.1
Name: sftpman-gtk
Version: 1.2.0
Summary: A GTK frontend for SftpMan, which helps you mount SFTP file systems.
Home-page: https://github.com/spantaleev/sftpman-gtk
Author: Slavi Pantaleev
Author-email: slavi@devture.com
License: GPL v3
Keywords: sftp,ssh,sshfs,gtk
Classifier: Programming Language :: Python
Classifier: Programming Language :: Python :: 3
Classifier: Development Status :: 5 - Production/Stable
Classifier: Environment :: X11 Applications :: GTK
Classifier: Intended Audience :: Developers
Classifier: Intended Audience :: System Administrators
Classifier: License :: OSI Approved :: GNU General Public License v3 (GPLv3)
Classifier: Operating System :: Unix
Classifier: Topic :: Communications :: File Sharing
Classifier: Topic :: Desktop Environment :: File Managers
Classifier: Topic :: Desktop Environment :: Gnome
Classifier: Topic :: Internet
Classifier: Topic :: Internet :: File Transfer Protocol (FTP)
Classifier: Topic :: System :: Networking
Classifier: Topic :: Utilities
License-File: LICENSE.txt
